asset_sentiment_analyzer/__init__.py
asset_sentiment_analyzer/apps.py
asset_sentiment_analyzer/gpt_client.py
asset_sentiment_analyzer/scrapper.py
asset_sentiment_analyzer/utils.py
asset_sentiment_analyzer/websearch_funcs.py
asset_sentiment_analyzer-0.1.4.dist-info/LICENSE
asset_sentiment_analyzer-0.1.4.dist-info/METADATA
asset_sentiment_analyzer-0.1.4.dist-info/WHEEL
asset_sentiment_analyzer-0.1.4.dist-info/top_level.txt
asset_sentiment_analyzer-0.1.4.dist-info/RECORD
