Metadata-Version: 2.1
Name: asset-sentiment-analyzer
Version: 0.1.4
Summary: A sentiment analyzer package for financial assets and securities utilizing GPT models.
Home-page: https://github.com/KVignesh122/AssetNewsSentimentAnalyzer
Author: Kumaravel Vignesh
Author-email: k_vignesh@hotmail.com
License: Apache-2.0
Platform: UNKNOWN
Classifier: Development Status :: 3 - Alpha
Classifier: Intended Audience :: Developers
Classifier: License :: OSI Approved :: Apache Software License
Classifier: Programming Language :: Python :: 3
Classifier: Programming Language :: Python :: 3.8
Classifier: Programming Language :: Python :: 3.9
Classifier: Programming Language :: Python :: 3.10
Requires-Python: >=3.6
License-File: LICENSE
Requires-Dist: requests
Requires-Dist: beautifulsoup4
Requires-Dist: readability-lxml
Requires-Dist: lxml-html-clean
Requires-Dist: tiktoken
Requires-Dist: openai
Requires-Dist: aiohttp
